tabviz/__init__.py
tabviz/static/example.twbx
tabviz/tabvizmain.py
tabviz-1.1.0.9.dist-info/entry_points.txt
tabviz-1.1.0.9.dist-info/LICENSE
tabviz-1.1.0.9.dist-info/METADATA
tabviz-1.1.0.9.dist-info/WHEEL
tabviz-1.1.0.9.dist-info/RECORD
