Metadata-Version: 2.1
Name: tabviz
Version: 1.1.0.9
Summary: A Python module for working with the Tableau
Home-page: https://github.com/AyushDhimann/TabViz
License: GNU
Keywords: Tableau,TabViz
Author: Ayush Dhiman
Author-email: ayushdhiman272@gmail.com
Requires-Python: >=3.7,<4.0
Classifier: License :: Other/Proprietary License
Classifier: Programming Language :: Python :: 3
Classifier: Programming Language :: Python :: 3.7
Classifier: Programming Language :: Python :: 3.8
Classifier: Programming Language :: Python :: 3.9
Classifier: Programming Language :: Python :: 3.10
Classifier: Programming Language :: Python :: 3.11
Classifier: Programming Language :: Python :: 3.12
Requires-Dist: starlette (>=0.37.2,<0.38.0)
Requires-Dist: tableauserverclient (>=0.30,<0.31)
Project-URL: Repository, https://github.com/AyushDhimann/TabViz
